COPYING
cq-studio-0.9.0-docs/faq.txt
cq-studio-0.9.0-docs/functionality.txt
cq-studio-0.9.0-docs/html/_images/example-project-object-transparency.png
cq-studio-0.9.0-docs/html/_images/example-project.png
cq-studio-0.9.0-docs/html/_images/v400-hotend-1.png
cq-studio-0.9.0-docs/html/_images/v400-hotend-2.png
cq-studio-0.9.0-docs/html/_images/view-1.png
cq-studio-0.9.0-docs/html/_images/view-2.png
cq-studio-0.9.0-docs/html/_images/view-3.png
cq-studio-0.9.0-docs/html/_images/view-4.png
cq-studio-0.9.0-docs/html/_static/alabaster.css
cq-studio-0.9.0-docs/html/_static/basic.css
cq-studio-0.9.0-docs/html/_static/custom.css
cq-studio-0.9.0-docs/html/_static/doctools.js
cq-studio-0.9.0-docs/html/_static/documentation_options.js
cq-studio-0.9.0-docs/html/_static/language_data.js
cq-studio-0.9.0-docs/html/_static/pygments.css
cq-studio-0.9.0-docs/html/_static/searchtools.js
cq-studio-0.9.0-docs/html/_static/sphinx_highlight.js
cq-studio-0.9.0-docs/html/faq.html
cq-studio-0.9.0-docs/html/functionality.html
cq-studio-0.9.0-docs/html/index.html
cq-studio-0.9.0-docs/html/install.html
cq-studio-0.9.0-docs/html/resources.html
cq-studio-0.9.0-docs/html/searchindex.js
cq-studio-0.9.0-docs/html/usage.html
cq-studio-0.9.0-docs/index.txt
cq-studio-0.9.0-docs/install.txt
cq-studio-0.9.0-docs/resources.txt
cq-studio-0.9.0-docs/usage.txt
cq_studio/__init__.py
cq_studio/colours.py
cq_studio/constants.py
cq_studio/defaults.py
cq_studio/py.typed
cq_studio/reloader.py
cq_studio/server.py
cq_studio/trigonometry.py
cq_studio/units.py
cq_studio/utils.py
cq_studio-0.9.0.dist-info/COPYING
cq_studio-0.9.0.dist-info/LICENSE
cq_studio-0.9.0.dist-info/METADATA
cq_studio-0.9.0.dist-info/WHEEL
cq_studio-0.9.0.dist-info/entry_points.txt
cq_studio-0.9.0.dist-info/RECORD
