Metadata-Version: 2.1
Name: cq-studio
Version: 0.9.0
Summary: Hot-reloading server for CadQuery 3D objects with in-browser viewer from yacv-server
Home-page: https://pyropus.ca/docs/cq-studio/
License: GPL-2.0-only
Keywords: model,3D,CAD,viewer,CadQuery,programmatic,modelling,server,hot-reload,editor,part,design
Author: Charles Cazabon
Author-email: charlesc-software-cqs@pyropus.ca
Requires-Python: >=3.10,<3.13
Classifier: Development Status :: 3 - Alpha
Classifier: Environment :: Console
Classifier: Environment :: Web Environment
Classifier: Intended Audience :: Education
Classifier: Intended Audience :: End Users/Desktop
Classifier: Intended Audience :: Manufacturing
Classifier: License :: OSI Approved :: GNU General Public License v2 (GPLv2)
Classifier: Operating System :: OS Independent
Classifier: Programming Language :: Python :: 3
Classifier: Programming Language :: Python :: 3.10
Classifier: Programming Language :: Python :: 3.11
Classifier: Programming Language :: Python :: 3.12
Classifier: Topic :: Multimedia :: Graphics :: 3D Modeling
Classifier: Topic :: Multimedia :: Graphics :: Viewers
Classifier: Topic :: Scientific/Engineering
Classifier: Topic :: Scientific/Engineering :: Visualization
Requires-Dist: build123d
Requires-Dist: cadquery (==2.5.2)
Requires-Dist: click
Requires-Dist: yacv-server
Project-URL: Documentation, https://pyropus.ca/docs/cq-studio/
Project-URL: Repository, https://github.com/ccazabon/cq-studio/
